wiiload/__init__.py
wiiload/__main__.py
wiiload/upload.py
wiiload/version.py
async_wiiload-1.0.5.dist-info/LICENSE
async_wiiload-1.0.5.dist-info/METADATA
async_wiiload-1.0.5.dist-info/WHEEL
async_wiiload-1.0.5.dist-info/top_level.txt
async_wiiload-1.0.5.dist-info/RECORD
